{"is_source_file": true, "format": "JavaScript", "description": "This file sets up an HTTP client using Axios, including configuration of base URL, request interceptors for adding auth tokens, and response handling logic. It exports functions and an Axios instance for making API calls within a React-based project.", "external_files": ["../state/store", "../config"], "external_methods": ["store.getState()"], "published": ["getBaseURL", "httpClient"], "classes": [], "methods": [{"name": "getBaseURL()", "description": "Returns the API base URL from a centralized configuration object.", "scope": "", "scopeKind": ""}], "calls": ["axios.create", "store.getState", "Promise.reject"], "search-terms": ["axios", "httpClient", "interceptors", "Authorization", "config.apiBaseUrl", "React_APP_", "src/services/supabase"], "state": 2, "file_id": 31, "knowledge_revision": 244, "git_revision": "6f9005f79a630b4a6078cf4f2b74f0c719456886", "revision_history": [{"75": ""}, {"135": "09e5b506ed8ba82189573ac92ae244dd6b904fef"}, {"244": "6f9005f79a630b4a6078cf4f2b74f0c719456886"}], "ctags": [{"_type": "tag", "name": "getBaseURL", "path": "/home/kavia/workspace/code-generation/gym-management-system-21100-21109/gym_manager_frontend/src/api/httpClient.js", "pattern": "/^export function getBaseURL() {$/", "language": "JavaScript", "kind": "function", "signature": "()"}, {"_type": "tag", "name": "httpClient", "path": "/home/kavia/workspace/code-generation/gym-management-system-21100-21109/gym_manager_frontend/src/api/httpClient.js", "pattern": "/^export const httpClient = axios.create({$/", "language": "JavaScript", "kind": "constant"}], "hash": "68e9fcb2ad1babbb8a59ef9f9f3c2d03", "format-version": 4, "code-base-name": "gym_manager_frontend", "filename": "gym_manager_frontend/src/api/httpClient.js"}