{"is_source_file": true, "format": "TypeScript/React", "description": "This file defines a React functional component 'Signup' for the user registration page in a gym management system. It handles user input for email and password, performs sign-up using context-based authentication, and displays success or error messages.", "external_files": ["../context/AuthContext"], "external_methods": ["useAuth"], "published": [], "classes": [], "methods": [{"name": "Signup", "description": "React functional component rendering the signup form, managing form state, handling submission, and displaying feedback messages."}], "calls": ["useAuth", "signUp"], "search-terms": ["Signup", "useAuth", "signUp", "React", "TypeScript", "Form", "authentication", "signup form"], "state": 2, "file_id": 89, "knowledge_revision": 298, "git_revision": "", "ctags": [], "hash": "c16a28e3818c2c97c0321b09c02cd83f", "format-version": 4, "code-base-name": "gym_manager_frontend", "filename": "gym_manager_frontend/src/pages/Signup.tsx", "revision_history": [{"298": ""}]}