{"is_source_file": false, "format": "", "description": "", "external_files": [], "external_methods": [], "published": [], "classes": [], "methods": [], "calls": [], "search-terms": ["RoleSelection", "/get-started", "useRegistrationStore", "RegistrationWizard", "Header.jsx", "/register/wizard", "localStorage", "registration", "RoleSelect", "registration.role"], "state": 2, "file_id": 101, "knowledge_revision": 345, "git_revision": "d153c4bd1276f6ee0f61cf87de2e4dcc86d97f33", "hash": "d40af9b0c5ab9c06ed1542eaaa60ba48", "format-version": 4, "code-base-name": "gym_manager_frontend", "filename": "gym_manager_frontend/docs/REGISTRATION_FLOW.md", "revision_history": [{"345": "d153c4bd1276f6ee0f61cf87de2e4dcc86d97f33"}]}